README.rst
locust_auto_test.py
setup.py
locustauto.egg-info/PKG-INFO
locustauto.egg-info/SOURCES.txt
locustauto.egg-info/dependency_links.txt
locustauto.egg-info/entry_points.txt
locustauto.egg-info/requires.txt
locustauto.egg-info/top_level.txt