Metadata-Version: 1.0
Name: locustauto
Version: 0.2.1
Summary: Automatically Test with Locust.io
Home-page: https://github.com/BenjiLee/locustauto
Author: Christopher Lee
Author-email: christopherlee2012@gmail.com
License: Apache2
Platform: UNKNOWN
